main.py
setup.py
res_adapter.egg-info/PKG-INFO
res_adapter.egg-info/SOURCES.txt
res_adapter.egg-info/dependency_links.txt
res_adapter.egg-info/requires.txt
res_adapter.egg-info/top_level.txt